spectrum/__init__.py
spectrum/client.py
spectrum/errors.py
spectrum/gateway.py
spectrum/http.py
spectrum/httpclient.py
spectrum/community/__init__.py
spectrum/community/client.py
spectrum/models/__init__.py
spectrum/models/activity.py
spectrum/models/badge.py
spectrum/models/channel.py
spectrum/models/community.py
spectrum/models/content.py
spectrum/models/emoji.py
spectrum/models/forum.py
spectrum/models/lobby.py
spectrum/models/member.py
spectrum/models/message.py
spectrum/models/object.py
spectrum/models/permissions.py
spectrum/models/presence.py
spectrum/models/reaction.py
spectrum/models/reply.py
spectrum/models/role.py
spectrum/models/thread.py
spectrum/models/abc/__init__.py
spectrum/models/abc/hasclient.py
spectrum/models/abc/identifier.py
spectrum/models/abc/subscription.py
spectrum/util/__init__.py
spectrum/util/datetime.py
spectrum/util/entity_ranges.py
spectrum/util/event_dispatch.py
spectrum/util/limited_size_dict.py
spectrum.py-0.0.10.dist-info/LICENSE
spectrum.py-0.0.10.dist-info/METADATA
spectrum.py-0.0.10.dist-info/WHEEL
spectrum.py-0.0.10.dist-info/top_level.txt
spectrum.py-0.0.10.dist-info/RECORD
