Metadata-Version: 2.1
Name: spectrum.py
Version: 0.0.10
Summary: spectrum.py is a [discord.py](https://github.com/Rapptz/discord.py) style proof-of-concept library for making chatbots for Star Citizen's [Spectrum](https://robertsspaceindustries.com/spectrum/community/SC) chat client.
Author: henry232323
License: The MIT License (MIT)
Project-URL: Homepage, http://github.com/henry232323/spectrum.py
Project-URL: Bug Tracker, http://github.com/henry232323/spectrum.py/issues
Classifier: Intended Audience :: Developers
Classifier: License :: OSI Approved :: MIT License
Classifier: Programming Language :: Python :: 3
Requires-Python: >=3.10
License-File: LICENSE
Requires-Dist: aiohttp
